pyKStroke/__init__.py
pyKStroke/ksApp.py
pyKStroke/ksSys.py
pyKStroke/docs/LICENSE
pyKStroke/docs/README.md
pyKStroke/docs/Reference.md
pyKStroke/ksApplication/AppGetchUnix.py
pyKStroke/ksApplication/AppGetchWindows.py
pyKStroke/ksApplication/__init__.py
pyKStroke/ksSystem/SysGetchMacCarbon.py
pyKStroke/ksSystem/SysGetchUnix.py
pyKStroke/ksSystem/SysGetchWindows.py
pyKStroke/ksSystem/__init__.py
pyKStroke-0.4.3.dist-info/DESCRIPTION.rst
pyKStroke-0.4.3.dist-info/METADATA
pyKStroke-0.4.3.dist-info/RECORD
pyKStroke-0.4.3.dist-info/WHEEL
pyKStroke-0.4.3.dist-info/metadata.json
pyKStroke-0.4.3.dist-info/top_level.txt
