Metadata-Version: 2.0
Name: pyKStroke
Version: 0.4.3
Summary: Simple keyboard input hook on multiple platforms that returns a character.
Home-page: https://bitbucket.org/Tungsteno/pykstroke/wiki/Home
Author: Tungsteno
Author-email: contacts00-pykstroke@yahoo.it
License: LGPLv2.1+
Download-URL: https://bitbucket.org/Tungsteno/pykstroke/get/0.4.3.zip
Keywords: input keyboard system events user control hook
Platform: UNKNOWN
Classifier: Development Status :: 4 - Beta
Classifier: Environment :: MacOS X :: Carbon
Classifier: Environment :: Win32 (MS Windows)
Classifier: Environment :: X11 Applications
Classifier: Topic :: System :: Monitoring
Classifier: Topic :: Software Development :: Libraries :: Python Modules
Classifier: License :: OSI Approved :: GNU Lesser General Public License v2 or later (LGPLv2+)
Classifier: Operating System :: Microsoft :: Windows
Classifier: Operating System :: MacOS
Classifier: Operating System :: POSIX
Classifier: Programming Language :: Python :: 2.7
Requires-Dist: python-xlib (>=0.16); sys_platform=='darwin'
Requires-Dist: python-xlib (>=0.16); sys_platform=='linux2'
Requires-Dist: pypiwin32 (>=218); sys_platform=='win32'
Requires-Dist: pyWinhook (>=1.5.2); sys_platform=='win32'
